[{"":"","AGÊNCIA DE EMPREGO":""},{"":"","AGÊNCIA DE EMPREGO":"AGENTE DE AÇÃO SOCIAL"},{"":"","AGÊNCIA DE EMPREGO":""},{"":"","AGÊNCIA DE EMPREGO":"R$1490"},{"":"","AGÊNCIA DE EMPREGO":"Recife / Bairro do Recife"},{"":"","AGÊNCIA DE EMPREGO":""},{"":"","AGÊNCIA DE EMPREGO":""},{"":"","AGÊNCIA DE EMPREGO":""},{"":"","AGÊNCIA DE EMPREGO":""},{"":"","AGÊNCIA DE EMPREGO":""},{"":"","AGÊNCIA DE EMPREGO":""},{"":"","AGÊNCIA DE EMPREGO":"AJUDANTE DE ELETRICISTA"},{"":"","AGÊNCIA DE EMPREGO":""},{"":"","AGÊNCIA DE EMPREGO":"R$954"},{"":"","AGÊNCIA DE EMPREGO":"Recife / Boa Viagem"},{"":"","AGÊNCIA DE EMPREGO":""},{"":"","AGÊNCIA DE EMPREGO":""},{"":"","AGÊNCIA DE EMPREGO":""},{"":"","AGÊNCIA DE EMPREGO":""},{"":"","AGÊNCIA DE EMPREGO":""},{"":"","AGÊNCIA DE EMPREGO":""},{"":"","AGÊNCIA DE EMPREGO":"ASSISTENTE DE PREVENÇÃO DE PERDAS"},{"":"","AGÊNCIA DE EMPREGO":""},{"":"","AGÊNCIA DE EMPREGO":"R$1000"},{"":"","AGÊNCIA DE EMPREGO":"Recife / Bairro do Recife"},{"":"","AGÊNCIA DE EMPREGO":""},{"":"","AGÊNCIA DE EMPREGO":""},{"":"","AGÊNCIA DE EMPREGO":""},{"":"","AGÊNCIA DE EMPREGO":""},{"":"","AGÊNCIA DE EMPREGO":""},{"":"","AGÊNCIA DE EMPREGO":""},{"":"","AGÊNCIA DE EMPREGO":"AUXILIAR ADMINISTRATIVO"},{"":"","AGÊNCIA DE EMPREGO":""},{"":"","AGÊNCIA DE EMPREGO":"R$1132"},{"":"","AGÊNCIA DE EMPREGO":"Recife / Soledade"},{"":"","AGÊNCIA DE EMPREGO":""},{"":"","AGÊNCIA DE EMPREGO":""},{"":"","AGÊNCIA DE EMPREGO":""},{"":"","AGÊNCIA DE EMPREGO":""},{"":"","AGÊNCIA DE EMPREGO":""},{"":"","AGÊNCIA DE EMPREGO":""},{"":"","AGÊNCIA DE EMPREGO":""},{"":"","AGÊNCIA DE EMPREGO":""},{"":"","AGÊNCIA DE EMPREGO":"AGÊNCIA DE EMPREGO"},{"":"","AGÊNCIA DE EMPREGO":""},{"":"","AGÊNCIA DE EMPREGO":"AUXILIAR DE ALMOXARIFADO"},{"":"","AGÊNCIA DE EMPREGO":""},{"":"","AGÊNCIA DE EMPREGO":"R$1019"},{"":"","AGÊNCIA DE EMPREGO":"Recife / Bairro do Recife"},{"":"","AGÊNCIA DE EMPREGO":""},{"":"","AGÊNCIA DE EMPREGO":""},{"":"","AGÊNCIA DE EMPREGO":""},{"":"","AGÊNCIA DE EMPREGO":""},{"":"","AGÊNCIA DE EMPREGO":""},{"":"","AGÊNCIA DE EMPREGO":""},{"":"","AGÊNCIA DE EMPREGO":"AUXILIAR FINANCEIRO"},{"":"","AGÊNCIA DE EMPREGO":""},{"":"","AGÊNCIA DE EMPREGO":"R$1200"},{"":"","AGÊNCIA DE EMPREGO":"Recife / Bairro do Recife"},{"":"","AGÊNCIA DE EMPREGO":""},{"":"","AGÊNCIA DE EMPREGO":""},{"":"","AGÊNCIA DE EMPREGO":""},{"":"","AGÊNCIA DE EMPREGO":""},{"":"","AGÊNCIA DE EMPREGO":""},{"":"","AGÊNCIA DE EMPREGO":""},{"":"","AGÊNCIA DE EMPREGO":"CHAVEIRO"},{"":"","AGÊNCIA DE EMPREGO":""},{"":"","AGÊNCIA DE EMPREGO":"R$954"},{"":"","AGÊNCIA DE EMPREGO":"Recife / Pina"},{"":"","AGÊNCIA DE EMPREGO":""},{"":"","AGÊNCIA DE EMPREGO":""},{"":"","AGÊNCIA DE EMPREGO":""},{"":"","AGÊNCIA DE EMPREGO":""},{"":"","AGÊNCIA DE EMPREGO":""},{"":"","AGÊNCIA DE EMPREGO":""},{"":"","AGÊNCIA DE EMPREGO":"ELETRICISTA"},{"":"","AGÊNCIA DE EMPREGO":""},{"":"","AGÊNCIA DE EMPREGO":"R$1200"},{"":"","AGÊNCIA DE EMPREGO":"Recife / Bairro do Recife"},{"":"","AGÊNCIA DE EMPREGO":""},{"":"","AGÊNCIA DE EMPREGO":""},{"":"","AGÊNCIA DE EMPREGO":""},{"":"","AGÊNCIA DE EMPREGO":""},{"":"","AGÊNCIA DE EMPREGO":""},{"":"","AGÊNCIA DE EMPREGO":""},{"":"","AGÊNCIA DE EMPREGO":""},{"":"","AGÊNCIA DE EMPREGO":""},{"":"","AGÊNCIA DE EMPREGO":"AGÊNCIA DE EMPREGO"},{"":"","AGÊNCIA DE EMPREGO":""},{"":"","AGÊNCIA DE EMPREGO":"GARAGISTA"},{"":"","AGÊNCIA DE EMPREGO":""},{"":"","AGÊNCIA DE EMPREGO":"R$1184"},{"":"","AGÊNCIA DE EMPREGO":"Recife / Ilha do Retiro"},{"":"","AGÊNCIA DE EMPREGO":""},{"":"","AGÊNCIA DE EMPREGO":""},{"":"","AGÊNCIA DE EMPREGO":""},{"":"","AGÊNCIA DE EMPREGO":""},{"":"","AGÊNCIA DE EMPREGO":""},{"":"","AGÊNCIA DE EMPREGO":""},{"":"","AGÊNCIA DE EMPREGO":"INSTRUTOR DE AUTO ESCOLA"},{"":"","AGÊNCIA DE EMPREGO":""},{"":"","AGÊNCIA DE EMPREGO":"R$1300"},{"":"","AGÊNCIA DE EMPREGO":"Recife / Imbiribeira"},{"":"","AGÊNCIA DE EMPREGO":""},{"":"","AGÊNCIA DE EMPREGO":""},{"":"","AGÊNCIA DE EMPREGO":""},{"":"","AGÊNCIA DE EMPREGO":""},{"":"","AGÊNCIA DE EMPREGO":""},{"":"","AGÊNCIA DE EMPREGO":""},{"":"","AGÊNCIA DE EMPREGO":"MOTORISTA DE ÔNIBUS URBANO"},{"":"","AGÊNCIA DE EMPREGO":""},{"":"","AGÊNCIA DE EMPREGO":"R$2253"},{"":"","AGÊNCIA DE EMPREGO":"Recife / Bairro do Recife"},{"":"","AGÊNCIA DE EMPREGO":""},{"":"","AGÊNCIA DE EMPREGO":""},{"":"","AGÊNCIA DE EMPREGO":""},{"":"","AGÊNCIA DE EMPREGO":""},{"":"","AGÊNCIA DE EMPREGO":""},{"":"","AGÊNCIA DE EMPREGO":""},{"":"","AGÊNCIA DE EMPREGO":"OPERADOR DE ESCAVADEIRA"},{"":"","AGÊNCIA DE EMPREGO":""},{"":"","AGÊNCIA DE EMPREGO":"R$1600"},{"":"","AGÊNCIA DE EMPREGO":"Recife / Soledade"},{"":"","AGÊNCIA DE EMPREGO":""},{"":"","AGÊNCIA DE EMPREGO":""},{"":"","AGÊNCIA DE EMPREGO":""},{"":"","AGÊNCIA DE EMPREGO":""},{"":"","AGÊNCIA DE EMPREGO":""},{"":"","AGÊNCIA DE EMPREGO":""},{"":"","AGÊNCIA DE EMPREGO":""},{"":"","AGÊNCIA DE EMPREGO":""},{"":"","AGÊNCIA DE EMPREGO":"AGÊNCIA DE EMPREGO"},{"":"","AGÊNCIA DE EMPREGO":""},{"":"","AGÊNCIA DE EMPREGO":"PORTEIRO"},{"":"","AGÊNCIA DE EMPREGO":""},{"":"","AGÊNCIA DE EMPREGO":"R$1000"},{"":"","AGÊNCIA DE EMPREGO":"Recife / Bairro do Recife"},{"":"","AGÊNCIA DE EMPREGO":""},{"":"","AGÊNCIA DE EMPREGO":""},{"":"","AGÊNCIA DE EMPREGO":""},{"":"","AGÊNCIA DE EMPREGO":""},{"":"","AGÊNCIA DE EMPREGO":""},{"":"","AGÊNCIA DE EMPREGO":""},{"":"","AGÊNCIA DE EMPREGO":"REPOSITOR DE MERCADORIAS"},{"":"","AGÊNCIA DE EMPREGO":""},{"":"","AGÊNCIA DE EMPREGO":"R$1000"},{"":"","AGÊNCIA DE EMPREGO":"Recife / Bairro do Recife"},{"":"","AGÊNCIA DE EMPREGO":""},{"":"","AGÊNCIA DE EMPREGO":""},{"":"","AGÊNCIA DE EMPREGO":""},{"":"","AGÊNCIA DE EMPREGO":""},{"":"","AGÊNCIA DE EMPREGO":""},{"":"","AGÊNCIA DE EMPREGO":""},{"":"","AGÊNCIA DE EMPREGO":"TRABALHADOR DE SERVIÇOS DE LIMPEZA E CONSERVAÇÃO DE ÁREAS PÚBLICAS"},{"":"","AGÊNCIA DE EMPREGO":""},{"":"","AGÊNCIA DE EMPREGO":"R$954"},{"":"","AGÊNCIA DE EMPREGO":"Recife / Bairro do Recife"},{"":"","AGÊNCIA DE EMPREGO":""},{"":"","AGÊNCIA DE EMPREGO":""},{"":"","AGÊNCIA DE EMPREGO":""},{"":"","AGÊNCIA DE EMPREGO":""},{"":"","AGÊNCIA DE EMPREGO":""},{"":"","AGÊNCIA DE EMPREGO":""},{"":"","AGÊNCIA DE EMPREGO":"VENDEDOR INTERNO"},{"":"","AGÊNCIA DE EMPREGO":""},{"":"","AGÊNCIA DE EMPREGO":"R$1000"},{"":"","AGÊNCIA DE EMPREGO":"Recife / Imbiribeira"},{"":"","AGÊNCIA DE EMPREGO":""},{"":"","AGÊNCIA DE EMPREGO":""},{"":"","AGÊNCIA DE EMPREGO":""},{"":"","AGÊNCIA DE EMPREGO":""},{"":"","AGÊNCIA DE EMPREGO":""},{"":"","AGÊNCIA DE EMPREGO":""},{"":"","AGÊNCIA DE EMPREGO":""},{"":"","AGÊNCIA DE EMPREGO":""},{"":"","AGÊNCIA DE EMPREGO":"AGÊNCIA DE EMPREGO"},{"":"","AGÊNCIA DE EMPREGO":""},{"":"","AGÊNCIA DE EMPREGO":"VENDEDOR PRACISTA"},{"":"","AGÊNCIA DE EMPREGO":""},{"":"","AGÊNCIA DE EMPREGO":"R$1100"},{"":"","AGÊNCIA DE EMPREGO":"Olinda / Águas Compridas"},{"":"","AGÊNCIA DE EMPREGO":""},{"":"","AGÊNCIA DE EMPREGO":""},{"":"","AGÊNCIA DE EMPREGO":""},{"":"","AGÊNCIA DE EMPREGO":""},{"":"","AGÊNCIA DE EMPREGO":""},{"":"","AGÊNCIA DE EMPREGO":""},{"":"","AGÊNCIA DE EMPREGO":""},{"":"","AGÊNCIA DE EMPREGO":""},{"":"","AGÊNCIA DE EMPREGO":"R$"},{"":"","AGÊNCIA DE EMPREGO":"/"},{"":"","AGÊNCIA DE EMPREGO":""},{"":"","AGÊNCIA DE EMPREGO":""},{"":"","AGÊNCIA DE EMPREGO":""},{"":"","AGÊNCIA DE EMPREGO":""},{"":"","AGÊNCIA DE EMPREGO":""},{"":"","AGÊNCIA DE EMPREGO":""},{"":"","AGÊNCIA DE EMPREGO":""},{"":"","AGÊNCIA DE EMPREGO":""},{"":"","AGÊNCIA DE EMPREGO":"R$"},{"":"","AGÊNCIA DE EMPREGO":"/"},{"":"","AGÊNCIA DE EMPREGO":""},{"":"","AGÊNCIA DE EMPREGO":""},{"":"","AGÊNCIA DE EMPREGO":""},{"":"","AGÊNCIA DE EMPREGO":""},{"":"","AGÊNCIA DE EMPREGO":""},{"":"","AGÊNCIA DE EMPREGO":""},{"":"","AGÊNCIA DE EMPREGO":""},{"":"","AGÊNCIA DE EMPREGO":""},{"":"","AGÊNCIA DE EMPREGO":"R$"},{"":"","AGÊNCIA DE EMPREGO":"/"},{"":"","AGÊNCIA DE EMPREGO":""},{"":"","AGÊNCIA DE EMPREGO":""},{"":"","AGÊNCIA DE EMPREGO":""},{"":"","AGÊNCIA DE EMPREGO":""},{"":"","AGÊNCIA DE EMPREGO":""},{"":"","AGÊNCIA DE EMPREGO":""},{"":"","AGÊNCIA DE EMPREGO":""},{"":"","AGÊNCIA DE EMPREGO":""},{"":"","AGÊNCIA DE EMPREGO":"AGÊNCIA DE EMPREGO"},{"":"","AGÊNCIA DE EMPREGO":""},{"":"","AGÊNCIA DE EMPREGO":""},{"":"","AGÊNCIA DE EMPREGO":""},{"":"","AGÊNCIA DE EMPREGO":"R$"},{"":"","AGÊNCIA DE EMPREGO":"/"},{"":"","AGÊNCIA DE EMPREGO":""},{"":"","AGÊNCIA DE EMPREGO":""},{"":"","AGÊNCIA DE EMPREGO":""},{"":"","AGÊNCIA DE EMPREGO":""},{"":"","AGÊNCIA DE EMPREGO":""},{"":"","AGÊNCIA DE EMPREGO":""},{"":"","AGÊNCIA DE EMPREGO":""},{"":"","AGÊNCIA DE EMPREGO":""},{"":"","AGÊNCIA DE EMPREGO":"R$"},{"":"","AGÊNCIA DE EMPREGO":"/"},{"":"","AGÊNCIA DE EMPREGO":""},{"":"","AGÊNCIA DE EMPREGO":""},{"":"","AGÊNCIA DE EMPREGO":""},{"":"","AGÊNCIA DE EMPREGO":""},{"":"","AGÊNCIA DE EMPREGO":""},{"":"","AGÊNCIA DE EMPREGO":""},{"":"","AGÊNCIA DE EMPREGO":""},{"":"","AGÊNCIA DE EMPREGO":""},{"":"","AGÊNCIA DE EMPREGO":"R$"},{"":"","AGÊNCIA DE EMPREGO":"/"},{"":"","AGÊNCIA DE EMPREGO":""},{"":"","AGÊNCIA DE EMPREGO":""},{"":"","AGÊNCIA DE EMPREGO":""},{"":"","AGÊNCIA DE EMPREGO":""},{"":"","AGÊNCIA DE EMPREGO":""},{"":"","AGÊNCIA DE EMPREGO":""},{"":"","AGÊNCIA DE EMPREGO":""},{"":"","AGÊNCIA DE EMPREGO":""},{"":"","AGÊNCIA DE EMPREGO":"R$"},{"":"","AGÊNCIA DE EMPREGO":"/"},{"":"","AGÊNCIA DE EMPREGO":""},{"":"","AGÊNCIA DE EMPREGO":""},{"":"","AGÊNCIA DE EMPREGO":""},{"":"","AGÊNCIA DE EMPREGO":""},{"":"","AGÊNCIA DE EMPREGO":""},{"":"","AGÊNCIA DE EMPREGO":""},{"":"","AGÊNCIA DE EMPREGO":""},{"":"","AGÊNCIA DE EMPREGO":""},{"":"","AGÊNCIA DE EMPREGO":"AGÊNCIA DE EMPREGO"},{"":"","AGÊNCIA DE EMPREGO":""},{"":"","AGÊNCIA DE EMPREGO":""},{"":"","AGÊNCIA DE EMPREGO":""},{"":"","AGÊNCIA DE EMPREGO":"R$"},{"":"","AGÊNCIA DE EMPREGO":"/"},{"":"","AGÊNCIA DE EMPREGO":""},{"":"","AGÊNCIA DE EMPREGO":""},{"":"","AGÊNCIA DE EMPREGO":""},{"":"","AGÊNCIA DE EMPREGO":""},{"":"","AGÊNCIA DE EMPREGO":""},{"":"","AGÊNCIA DE EMPREGO":""},{"":"","AGÊNCIA DE EMPREGO":""},{"":"","AGÊNCIA DE EMPREGO":""},{"":"","AGÊNCIA DE EMPREGO":"R$"},{"":"","AGÊNCIA DE EMPREGO":"/"},{"":"","AGÊNCIA DE EMPREGO":""},{"":"","AGÊNCIA DE EMPREGO":""},{"":"","AGÊNCIA DE EMPREGO":""},{"":"","AGÊNCIA DE EMPREGO":""},{"":"","AGÊNCIA DE EMPREGO":""},{"":"","AGÊNCIA DE EMPREGO":""},{"":"","AGÊNCIA DE EMPREGO":""},{"":"","AGÊNCIA DE EMPREGO":""},{"":"","AGÊNCIA DE EMPREGO":"R$"},{"":"","AGÊNCIA DE EMPREGO":"/"},{"":"","AGÊNCIA DE EMPREGO":""},{"":"","AGÊNCIA DE EMPREGO":""},{"":"","AGÊNCIA DE EMPREGO":""},{"":"","AGÊNCIA DE EMPREGO":""},{"":"","AGÊNCIA DE EMPREGO":""},{"":"","AGÊNCIA DE EMPREGO":""},{"":"","AGÊNCIA DE EMPREGO":""},{"":"","AGÊNCIA DE EMPREGO":""},{"":"","AGÊNCIA DE EMPREGO":"R$"},{"":"","AGÊNCIA DE EMPREGO":"/"},{"":"","AGÊNCIA DE EMPREGO":""},{"":"","AGÊNCIA DE EMPREGO":""},{"":"","AGÊNCIA DE EMPREGO":""},{"":"","AGÊNCIA DE EMPREGO":""},{"":"","AGÊNCIA DE EMPREGO":""},{"":"","AGÊNCIA DE EMPREGO":""},{"":"","AGÊNCIA DE EMPREGO":""},{"":"","AGÊNCIA DE EMPREGO":""},{"":"","AGÊNCIA DE EMPREGO":"AGÊNCIA DE EMPREGO"},{"":"","AGÊNCIA DE EMPREGO":""},{"":"","AGÊNCIA DE EMPREGO":""},{"":"","AGÊNCIA DE EMPREGO":""},{"":"","AGÊNCIA DE EMPREGO":"R$"},{"":"","AGÊNCIA DE EMPREGO":"/"},{"":"","AGÊNCIA DE EMPREGO":""},{"":"","AGÊNCIA DE EMPREGO":""},{"":"","AGÊNCIA DE EMPREGO":""},{"":"","AGÊNCIA DE EMPREGO":""},{"":"","AGÊNCIA DE EMPREGO":""},{"":"","AGÊNCIA DE EMPREGO":""},{"":"","AGÊNCIA DE EMPREGO":""},{"":"","AGÊNCIA DE EMPREGO":""},{"":"","AGÊNCIA DE EMPREGO":"R$"},{"":"","AGÊNCIA DE EMPREGO":"/"},{"":"","AGÊNCIA DE EMPREGO":""},{"":"","AGÊNCIA DE EMPREGO":""},{"":"","AGÊNCIA DE EMPREGO":""},{"":"","AGÊNCIA DE EMPREGO":""},{"":"","AGÊNCIA DE EMPREGO":""},{"":"","AGÊNCIA DE EMPREGO":""},{"":"","AGÊNCIA DE EMPREGO":""},{"":"","AGÊNCIA DE EMPREGO":""},{"":"","AGÊNCIA DE EMPREGO":"R$"},{"":"","AGÊNCIA DE EMPREGO":"/"},{"":"","AGÊNCIA DE EMPREGO":""},{"":"","AGÊNCIA DE EMPREGO":""},{"":"","AGÊNCIA DE EMPREGO":""},{"":"","AGÊNCIA DE EMPREGO":""},{"":"","AGÊNCIA DE EMPREGO":""},{"":"","AGÊNCIA DE EMPREGO":""},{"":"","AGÊNCIA DE EMPREGO":""},{"":"","AGÊNCIA DE EMPREGO":""},{"":"","AGÊNCIA DE EMPREGO":"R$"},{"":"","AGÊNCIA DE EMPREGO":"/"},{"":"","AGÊNCIA DE EMPREGO":""},{"":"","AGÊNCIA DE EMPREGO":""},{"":"","AGÊNCIA DE EMPREGO":""},{"":"","AGÊNCIA DE EMPREGO":""},{"":"","AGÊNCIA DE EMPREGO":""},{"":"","AGÊNCIA DE EMPREGO":""},{"":"","AGÊNCIA DE EMPREGO":""},{"":"","AGÊNCIA DE EMPREGO":""},{"":"","AGÊNCIA DE EMPREGO":"AGÊNCIA DE EMPREGO"},{"":"","AGÊNCIA DE EMPREGO":""},{"":"","AGÊNCIA DE EMPREGO":""},{"":"","AGÊNCIA DE EMPREGO":""},{"":"","AGÊNCIA DE EMPREGO":"R$"},{"":"","AGÊNCIA DE EMPREGO":"/"},{"":"","AGÊNCIA DE EMPREGO":""},{"":"","AGÊNCIA DE EMPREGO":""},{"":"","AGÊNCIA DE EMPREGO":""},{"":"","AGÊNCIA DE EMPREGO":""},{"":"","AGÊNCIA DE EMPREGO":""},{"":"","AGÊNCIA DE EMPREGO":""},{"":"","AGÊNCIA DE EMPREGO":""},{"":"","AGÊNCIA DE EMPREGO":""},{"":"","AGÊNCIA DE EMPREGO":"R$"},{"":"","AGÊNCIA DE EMPREGO":"/"},{"":"","AGÊNCIA DE EMPREGO":""},{"":"","AGÊNCIA DE EMPREGO":""},{"":"","AGÊNCIA DE EMPREGO":""},{"":"","AGÊNCIA DE EMPREGO":""},{"":"","AGÊNCIA DE EMPREGO":""},{"":"","AGÊNCIA DE EMPREGO":""},{"":"","AGÊNCIA DE EMPREGO":""},{"":"","AGÊNCIA DE EMPREGO":""},{"":"","AGÊNCIA DE EMPREGO":"R$"},{"":"","AGÊNCIA DE EMPREGO":"/"},{"":"","AGÊNCIA DE EMPREGO":""},{"":"","AGÊNCIA DE EMPREGO":""},{"":"","AGÊNCIA DE EMPREGO":""},{"":"","AGÊNCIA DE EMPREGO":""},{"":"","AGÊNCIA DE EMPREGO":""},{"":"","AGÊNCIA DE EMPREGO":""},{"":"","AGÊNCIA DE EMPREGO":""},{"":"","AGÊNCIA DE EMPREGO":""},{"":"","AGÊNCIA DE EMPREGO":"R$"},{"":"","AGÊNCIA DE EMPREGO":"/"},{"":"","AGÊNCIA DE EMPREGO":""},{"":"","AGÊNCIA DE EMPREGO":""},{"":"","AGÊNCIA DE EMPREGO":""},{"":"","AGÊNCIA DE EMPREGO":""},{"":"","AGÊNCIA DE EMPREGO":""},{"":"","AGÊNCIA DE EMPREGO":""},{"":"","AGÊNCIA DE EMPREGO":""}]